attrsmarkup/__init__.py
attrsmarkup/about.py
attrsmarkup-23.2.0.dist-info/METADATA
attrsmarkup-23.2.0.dist-info/WHEEL
attrsmarkup-23.2.0.dist-info/RECORD
